Workbook
Name Aporte: Simulador!$D$15
Name Patrimonio: Simulador!$D$18
Name qtd_anos: Simulador!$D$16
Name Rendimento_Carteira: Simulador!$D$11
Name Salario: Simulador!$D$10
Name Sugestao_Invest: Simulador!$D$12
Name Taxa_Mensal: Simulador!$D$17

Sheet Simulador
B9: CONFIGURAÇÕES
B10: Salário | D10: 5000
B11: Rendimento Carteira | D11: 0.006
B12: Sugestão de Investimento | D12: =D10*30% -> 1500
B14: INVESTIMENTO MENSAL
B15: Quanto investir por mês? | D15: 500
B16: Por quantos anos? | D16: 5
B17: Taxa de Rendimento Mensal? | D17: 0.01079
B18: Quanto de patrimonio acumulado? | D18: =FV(Taxa_Mensal,qtd_anos*12,Aporte*-1) -> 41888.457
B19: Dividendos Mensais | D19: =Patrimonio*Rendimento_Carteira -> 251.33074
B21: CENÁRIOS | D21: Dividendo
A22: 2 | B22: Quanto em 2 anos? | C22: =FV($D$17,$A22*12,$D$15*-1) -> 13613.814 | D22: =C22*Rendimento_Carteira -> 81.682882
A23: 5 | B23: Quantos em 5 anos? | C23: =FV($D$17,$A23*12,$D$15*-1) -> 41888.457 | D23: =C23*Rendimento_Carteira -> 251.33074
A24: 10 | B24: Quantos em 10 anos? | C24: =FV($D$17,$A24*12,$D$15*-1) -> 121642.11 | D24: =C24*Rendimento_Carteira -> 729.85264
A25: 20 | B25: Quantos em 20 anos? | C25: =FV($D$17,$A25*12,$D$15*-1) -> 562599.2 | D25: =C25*Rendimento_Carteira -> 3375.5952
A26: 30 | B26: Quantos em 30 anos? | C26: =FV($D$17,$A26*12,$D$15*-1) -> 2161084.8 | D26: =C26*Rendimento_Carteira -> 12966.509
B30: PERFIL | C30: Moderado
B31: VALOR A SER INVESTIDO POR MÊS | C31: =Aporte -> 500
B33: TIPOS DE FII | C33: PERCENTUAL SUGERIDO | D33: VALORES
B34: Papel | C34: =VLOOKUP($C$30&B34,Apoio!A:D,4,FALSE) -> 0.32 | D34: =C34*$C$31 -> 160
B35: Tijolo | C35: =VLOOKUP($C$30&B35,Apoio!A:D,4,FALSE) -> 0.35 | D35: =C35*$C$31 -> 175
B36: Híbrido | C36: =VLOOKUP($C$30&B36,Apoio!A:D,4,FALSE) -> 0.08 | D36: =C36*$C$31 -> 40
B37: FOFs | C37: =VLOOKUP($C$30&B37,Apoio!A:D,4,FALSE) -> 0.05 | D37: =C37*$C$31 -> 25
B38: Desenvolvimento | C38: =VLOOKUP($C$30&B38,Apoio!A:D,4,FALSE) -> 0.1 | D38: =C38*$C$31 -> 50
B39: Hotelarias | C39: =VLOOKUP($C$30&B39,Apoio!A:D,4,FALSE) -> 0.1 | D39: =C39*$C$31 -> 50
D40: =SUM(D34:D39) -> 500
C56: #VALUE!

Sheet Apoio
A1: CHAVE | B1: Perfil | C1: TIPOS DE FII | D1: %
A2: =B2&C2 -> ConservadorPapel | B2: Conservador | C2: Papel | D2: 0.3
A3: =B3&C3 -> ConservadorTijolo | B3: Conservador | C3: Tijolo | D3: 0.5
A4: =B4&C4 -> ConservadorHíbrido | B4: Conservador | C4: Híbrido | D4: 0.1
A5: =B5&C5 -> ConservadorFOFs | B5: Conservador | C5: FOFs | D5: 0.1 | I5: =J5&K5
A6: =B6&C6 -> ConservadorDesenvolvimento | B6: Conservador | C6: Desenvolvimento | D6: 0
A7: =B7&C7 -> ConservadorHotelarias | B7: Conservador | C7: Hotelarias | D7: 0 | J7: ModeradoTijolo | K7: =VLOOKUP(J7,A:D,4,0) -> 0.35
A8: =B8&C8 -> ModeradoPapel | B8: Moderado | C8: Papel | D8: 0.32
A9: =B9&C9 -> ModeradoTijolo | B9: Moderado | C9: Tijolo | D9: 0.35
A10: =B10&C10 -> ModeradoHíbrido | B10: Moderado | C10: Híbrido | D10: 0.08
A11: =B11&C11 -> ModeradoFOFs | B11: Moderado | C11: FOFs | D11: 0.05
A12: =B12&C12 -> ModeradoDesenvolvimento | B12: Moderado | C12: Desenvolvimento | D12: 0.1
A13: =B13&C13 -> ModeradoHotelarias | B13: Moderado | C13: Hotelarias | D13: 0.1
A14: =B14&C14 -> AgressivoPapel | B14: Agressivo | C14: Papel | D14: 0.5
A15: =B15&C15 -> AgressivoTijolo | B15: Agressivo | C15: Tijolo | D15: 0.1
A16: =B16&C16 -> AgressivoHíbrido | B16: Agressivo | C16: Híbrido | D16: 0.05
A17: =B17&C17 -> AgressivoFOFs | B17: Agressivo | C17: FOFs | D17: 0.05
A18: =B18&C18 -> AgressivoDesenvolvimento | B18: Agressivo | C18: Desenvolvimento | D18: 0.2
A19: =B19&C19 -> AgressivoHotelarias | B19: Agressivo | C19: Hotelarias | D19: 0.1
